{
   "CodeGenerationMode": 2,
   "ContextClassName": "FdbaDbContext",
   "ContextNamespace": null,
   "DefaultDacpacSchema": null,
   "FilterSchemas": false,
   "IncludeConnectionString": false,
   "ModelNamespace": null,
   "OutputContextPath": null,
   "OutputPath": "Entities",
   "PreserveCasingWithRegex": true,
   "ProjectRootNamespace": "DataAccess",
   "Schemas": null,
   "SelectedHandlebarsLanguage": 0,
   "SelectedToBeGenerated": 0,
   "Tables": [
      {
         "Name": "[fdba].[BusinessModule]",
         "ObjectType": 0
      },
      {
         "Name": "[fdba].[BusinessObject]",
         "ObjectType": 0
      },
      {
         "Name": "[fdba].[BusinessObjectExpression]",
         "ObjectType": 0
      },
      {
         "Name": "[fdba].[BusinessObjectGroup]",
         "ObjectType": 0
      },
      {
         "Name": "[fdba].[BusinessObjectRelation]",
         "ObjectType": 0
      },
      {
         "Name": "[fdba].[BusinessProperty]",
         "ObjectType": 0
      },
      {
         "Name": "[fdba].[BusinessPropertyType]",
         "ObjectType": 0
      },
      {
         "Name": "[fdba].[Container]",
         "ObjectType": 0
      },
      {
         "Name": "[fdba].[ContainerRole]",
         "ObjectType": 0
      },
      {
         "Name": "[fdba].[DatabaseDataType]",
         "ObjectType": 0
      },
      {
         "Name": "[fdba].[DatabaseInfo]",
         "ObjectType": 0
      },
      {
         "Name": "[fdba].[EnumerationType]",
         "ObjectType": 0
      },
      {
         "Name": "[fdba].[EnumerationValue]",
         "ObjectType": 0
      },
      {
         "Name": "[fdba].[ExpressionNode]",
         "ObjectType": 0
      },
      {
         "Name": "[fdba].[ForeignKey]",
         "ObjectType": 0
      },
      {
         "Name": "[fdba].[ImportPropertyInfo]",
         "ObjectType": 0
      },
      {
         "Name": "[fdba].[MappingProperties]",
         "ObjectType": 0
      },
      {
         "Name": "[fdba].[MetadataItemPathRelation]",
         "ObjectType": 0
      },
      {
         "Name": "[fdba].[Page]",
         "ObjectType": 0
      },
      {
         "Name": "[fdba].[Permission]",
         "ObjectType": 0
      },
      {
         "Name": "[fdba].[Role]",
         "ObjectType": 0
      },
      {
         "Name": "[fdba].[RoleUser]",
         "ObjectType": 0
      },
      {
         "Name": "[fdba].[User]",
         "ObjectType": 0
      },
      {
         "Name": "[fdba].[UsersGroup]",
         "ObjectType": 0
      },
      {
         "Name": "[fdba].[UserUsersGroup]",
         "ObjectType": 0
      }
   ],
   "UiHint": "desktop-1n0e7t6.FdbaDb.dbo",
   "UncountableWords": null,
   "UseBoolPropertiesWithoutDefaultSql": false,
   "UseDatabaseNames": false,
   "UseDbContextSplitting": true,
   "UseFluentApiOnly": true,
   "UseHandleBars": false,
   "UseHierarchyId": false,
   "UseInflector": true,
   "UseLegacyPluralizer": false,
   "UseManyToManyEntity": true,
   "UseNoDefaultConstructor": false,
   "UseNoObjectFilter": false,
   "UseNodaTime": false,
   "UseNullableReferences": false,
   "UseSchemaFolders": false,
   "UseSpatial": false,
   "UseT4": false
}